sphinxcontrib_rust/__init__.py
sphinxcontrib_rust/directives.py
sphinxcontrib_rust/domain.py
sphinxcontrib_rust/index.py
sphinxcontrib_rust/items.py
sphinxcontrib_rust/nodes.py
sphinxcontrib_rust/rust_link.py
sphinxcontrib_rust-0.6.1.dist-info/LICENSE
sphinxcontrib_rust-0.6.1.dist-info/METADATA
sphinxcontrib_rust-0.6.1.dist-info/WHEEL
sphinxcontrib_rust-0.6.1.dist-info/top_level.txt
sphinxcontrib_rust-0.6.1.dist-info/RECORD
