Metadata-Version: 2.1
Name: sphinxcontrib-rust
Version: 0.6.1
Summary: Sphinx extension for documenting Rust projects
Home-page: https://gitlab.com/munir0b0t/sphinxcontrib-rust
Author: Munir Contractor
Classifier: Development Status :: 4 - Beta
Classifier: Framework :: Sphinx :: Domain
Classifier: License :: OSI Approved :: GNU General Public License v3 or later (GPLv3+)
Classifier: Programming Language :: Rust
Classifier: Topic :: Documentation :: Sphinx
Requires-Python: >=3.9
License-File: LICENSE
Requires-Dist: sphinx <9,>=7
Requires-Dist: myst-parser <4,>=3
Provides-Extra: dev
Requires-Dist: black ; extra == 'dev'
Requires-Dist: pylint ; extra == 'dev'
Requires-Dist: pytest-cov ; extra == 'dev'
Requires-Dist: sphinx-rtd-theme ; extra == 'dev'
